kyla/__init__.py
kyla/script.py
kyla-0.0.1.dist-info/METADATA
kyla-0.0.1.dist-info/WHEEL
kyla-0.0.1.dist-info/top_level.txt
kyla-0.0.1.dist-info/RECORD
