Metadata-Version: 2.1
Name: kyla
Version: 0.0.1
Summary: A string utility tool
Home-page: https://github.com/firzaelbuho/pyhelloworld
Author: Firza Aditya 
Author-email: elbuho1315@gmail.com
Classifier: Programming Language :: Python :: 3
Classifier: License :: OSI Approved :: MIT License
Classifier: Operating System :: OS Independent
Requires-Python: >=3.6
